SpectraSimulations/SpectraSimulation.py
SpectraSimulations/SpectraSimulation_headless.py
SpectraSimulations/__init__.py
SpectraSimulations/__main__.py
SpectraSimulations/setup.py
SpectraSimulations/29/29-intensity.out
SpectraSimulations/aps/LvlWidths.py
SpectraSimulations/aps/SpecSimu.py
SpectraSimulations/aps/XRFQuant.py
SpectraSimulations/aps/Yields.py
SpectraSimulations/aps/__init__.py
SpectraSimulations/aps/initializers.py
SpectraSimulations/conversionScripts/__init__.py
SpectraSimulations/conversionScripts/scripts/__init__.py
SpectraSimulations/conversionScripts/scripts/masterConverter.py
SpectraSimulations/conversionScripts/scripts/restrict.py
SpectraSimulations/conversionScripts/scripts/auger/Calculate_aug_widths.py
SpectraSimulations/conversionScripts/scripts/auger/Calculate_auger_BR.py
SpectraSimulations/conversionScripts/scripts/auger/ConversionScript_auger_rates.py
SpectraSimulations/conversionScripts/scripts/auger/ConversionScript_auger_spectra.py
SpectraSimulations/conversionScripts/scripts/auger/__init__.py
SpectraSimulations/conversionScripts/scripts/diagram/Calculate_diagram_BR.py
SpectraSimulations/conversionScripts/scripts/diagram/Calculate_diagram_widths.py
SpectraSimulations/conversionScripts/scripts/diagram/ConversionScript_intensity_rates.py
SpectraSimulations/conversionScripts/scripts/diagram/ConversionScript_intensity_spectra.py
SpectraSimulations/conversionScripts/scripts/diagram/__init__.py
SpectraSimulations/conversionScripts/scripts/excitation/ConversionScript_excitation_spectra.py
SpectraSimulations/conversionScripts/scripts/excitation/__init__.py
SpectraSimulations/data/__init__.py
SpectraSimulations/data/clustering.py
SpectraSimulations/data/definitions.py
SpectraSimulations/data/variables.py
SpectraSimulations/data/wrappers.py
SpectraSimulations/dbs/ElamDB12.txt
SpectraSimulations/dbs/NIST_LineClusters.txt
SpectraSimulations/dbs/NIST_XrayLines.txt
SpectraSimulations/interface/__init__.py
SpectraSimulations/interface/base.py
SpectraSimulation-0.2.0.dist-info/LICENSE
SpectraSimulation-0.2.0.dist-info/METADATA
SpectraSimulation-0.2.0.dist-info/WHEEL
SpectraSimulation-0.2.0.dist-info/entry_points.txt
SpectraSimulation-0.2.0.dist-info/top_level.txt
SpectraSimulation-0.2.0.dist-info/RECORD
