Metadata-Version: 2.1
Name: SpectraSimulation
Version: 0.2.0
Summary: Simulation Program for calculating synthetic spectra from theoretical data.
Home-page: https://github.com/DSPinheiro/SpectraSimulations
Author: Daniel Pinheiro
Author-email: ds.pinheiro@campus.fct.unl.pt
License: MIT
Classifier: Development Status :: 4 - Beta
Classifier: Intended Audience :: Science/Research
Classifier: License :: OSI Approved :: MIT License
Classifier: Operating System :: OS Independent
Classifier: Programming Language :: Python :: 3
License-File: LICENSE
Requires-Dist: tk
Requires-Dist: numpy
Requires-Dist: scipy
Requires-Dist: lmfit
Requires-Dist: matplotlib
Requires-Dist: plotly
Requires-Dist: mplcursors
Requires-Dist: scikit-learn
Requires-Dist: pybaselines
Requires-Dist: iminuit
Requires-Dist: scienceplots
